data_quality_sdk/__init__.py
data_quality_sdk/checks.py
data_quality_sdk/config.py
data_quality_sdk/data_ingestion.py
data_quality_sdk/dq_ops.py
data_quality_sdk/logger.py
data_quality_sdk/metrics_publisher.py
data_quality_sdk-0.1.5.dist-info/LICENSE
data_quality_sdk-0.1.5.dist-info/METADATA
data_quality_sdk-0.1.5.dist-info/WHEEL
data_quality_sdk-0.1.5.dist-info/top_level.txt
data_quality_sdk-0.1.5.dist-info/RECORD
