Metadata-Version: 2.1
Name: data-quality-sdk
Version: 0.1.5
Summary: A Data Quality SDK for real-time metrics and checks.
Home-page: UNKNOWN
Author: Suraj Chaudhary
Author-email: suraj.chaudhary@xenonstack.com
License: UNKNOWN
Platform: UNKNOWN
License-File: LICENSE
Requires-Dist: delta-spark
Requires-Dist: kafka-python
Requires-Dist: pandas
Requires-Dist: pyyaml
